ape_pokt/__init__.py
ape_pokt/providers.py
ape_pokt/py.typed
ape_pokt/version.py
ape_pokt-0.1.2.dist-info/LICENSE
ape_pokt-0.1.2.dist-info/METADATA
ape_pokt-0.1.2.dist-info/WHEEL
ape_pokt-0.1.2.dist-info/top_level.txt
ape_pokt-0.1.2.dist-info/RECORD
